_ctl.cp39-win_amd64.pyd
ctl/__init__.py
ctl/gui.py
ctl/cl_src/processing/apodization_filter.cl
ctl/cl_src/processing/cosine_weighting.cl
ctl/cl_src/processing/homToRadon.cl
ctl/cl_src/processing/imageResampler.cl
ctl/cl_src/processing/parker_weighting.cl
ctl/cl_src/processing/planeIntegral.cl
ctl/cl_src/processing/radon2d.cl
ctl/cl_src/processing/radonToHom.cl
ctl/cl_src/processing/ramlak_filter.cl
ctl/cl_src/processing/rev_parker_weighting.cl
ctl/cl_src/processing/volumeResampler.cl
ctl/cl_src/processing/volumeSlicer.cl
ctl/cl_src/projectors/external_raycaster.cl
ctl/cl_src/projectors/projection_tr.cl
ctl/cl_src/projectors/projection_tr_atomicFloat.cl
ctl/cl_src/projectors/projection_tt.cl
ctl/cl_src/projectors/projection_tt_atomicFloat.cl
ctl/cl_src/projectors/projection_tt_generic.cl
ctl/cl_src/projectors/projection_tt_generic_atomicFloat.cl
ctl/cl_src/projectors/projection_tt_generic_sparse.cl
ctl/cl_src/projectors/projection_tt_generic_sparse_atomicFloat.cl
ctl/cl_src/projectors/raycasterprojector_interp.cl
ctl/cl_src/projectors/raycasterprojector_no_images.cl
ctl/cl_src/projectors/raycasterprojector_no_interp.cl
ctl/cl_src/recon/backprojection_tr.cl
ctl/cl_src/recon/backprojection_tt.cl
ctl/cl_src/recon/backprojection_tt_generic.cl
ctl/cl_src/recon/huber_regularizer.cl
ctl/cl_src/recon/nullifier.cl
ctl/cl_src/recon/simple_backprojector.cl
ctl/cl_src/recon/tv_regularizer.cl
ctl/database/references.md
ctl/database/attenuation_spectra/a150.json
ctl/database/attenuation_spectra/adipose.json
ctl/database/attenuation_spectra/air.json
ctl/database/attenuation_spectra/alanine.json
ctl/database/attenuation_spectra/b100.json
ctl/database/attenuation_spectra/bakelite.json
ctl/database/attenuation_spectra/blood.json
ctl/database/attenuation_spectra/bone.json
ctl/database/attenuation_spectra/brain.json
ctl/database/attenuation_spectra/breast.json
ctl/database/attenuation_spectra/c552.json
ctl/database/attenuation_spectra/calcium.json
pyctl-0.1.4.dist-info/METADATA
pyctl-0.1.4.dist-info/WHEEL
pyctl-0.1.4.dist-info/top_level.txt
pyctl-0.1.4.dist-info/RECORD
