Metadata-Version: 2.1
Name: pyctl
Version: 0.1.4
Summary: Python bindings for CTL
Home-page: https://github.com/phernst/pyctl
Author: Philipp Ernst
Author-email: philipp.ernst@ovgu.de
License: UNKNOWN
Platform: UNKNOWN
Requires-Dist: PySide2 (>=5.15)
Requires-Dist: importlib-resources ; python_version < "3.7"
